sinai/__init__.py
sinai/exceptions.py
sinai/py.typed
sinai/types.py
sinai/adaptors/__init__.py
sinai/adaptors/api.py
sinai/adaptors/memory.py
sinai/adaptors/mongo.py
sinai/adaptors/postgresql.py
sinai/metrics/__init__.py
sinai/metrics/aggregation.py
sinai/metrics/base.py
sinai/monitors/__init__.py
sinai/monitors/base.py
sinai/rules/__init__.py
sinai/rules/aggregation.py
sinai/rules/base.py
sinai/sources/__init__.py
sinai/sources/api.py
sinai/sources/base.py
sinai/sources/mongo.py
sinai/sources/postgresql.py
sinai/stores/__init__.py
sinai/stores/api.py
sinai/stores/base.py
sinai/stores/cloudwatch.py
sinai/stores/debug.py
sinai/stores/memory.py
sinai/stores/mongo.py
sinai/stores/slack.py
sinai-0.1.14.dist-info/METADATA
sinai-0.1.14.dist-info/WHEEL
sinai-0.1.14.dist-info/licenses/LICENSE
sinai-0.1.14.dist-info/RECORD
