Metadata-Version: 2.1
Name: sinai
Version: 0.1.14
Summary: Your friendly neighbourhood monitoring library. Record metrics about whatever you are interested in (e.g. application state, data integrity).
Project-URL: Homepage, https://github.com/SinAI-monitoring/sinai
Author: andymason,zeth
License-File: LICENSE
